setup.py
distributions_mbewu/Binomialdistribution.py
distributions_mbewu/Gaussiandistribution.py
distributions_mbewu/Generaldistribution.py
distributions_mbewu/__init__.py
distributions_mbewu.egg-info/PKG-INFO
distributions_mbewu.egg-info/SOURCES.txt
distributions_mbewu.egg-info/dependency_links.txt
distributions_mbewu.egg-info/not-zip-safe
distributions_mbewu.egg-info/top_level.txt