Metadata-Version: 1.0
Name: distributions-mbewu
Version: 0.1
Summary: Gaussian and Binomial distributions
Home-page: UNKNOWN
Author: James Mbewu
Author-email: james.mbewu@gmail.com
License: UNKNOWN
Platform: UNKNOWN
